__main__.py
cli.py
subxx.py
subxx-0.4.2.dist-info/METADATA
subxx-0.4.2.dist-info/WHEEL
subxx-0.4.2.dist-info/entry_points.txt
subxx-0.4.2.dist-info/licenses/LICENSE
subxx-0.4.2.dist-info/RECORD
