Metadata-Version: 2.4
Name: subxx
Version: 0.4.2
Summary: YouTube transcript / subtitle fetching toolkit for Python. Provides command line and HTTP interfaces. Supports language selection, SRT or VTT output
Project-URL: Homepage, https://gist.github.com/cprima/subxx
Project-URL: Documentation, https://gist.github.com/cprima/subxx
Project-URL: Repository, https://gist.github.com/cprima/subxx
Author-email: Christian Prior-Mamulyan <cprior@gmail.com>
License: Apache-2.0
License-File: LICENSE
Keywords: api,cli,subtitles,youtube,yt-dlp
Classifier: Development Status :: 3 - Alpha
Classifier: Intended Audience :: Developers
Classifier: License :: OSI Approved :: Apache Software License
Classifier: Programming Language :: Python :: 3
Classifier: Programming Language :: Python :: 3.9
Classifier: Programming Language :: Python :: 3.10
Classifier: Programming Language :: Python :: 3.11
Classifier: Programming Language :: Python :: 3.12
Classifier: Topic :: Multimedia :: Video
Requires-Python: >=3.9
Requires-Dist: beautifulsoup4>=4.14.2
Requires-Dist: curl-cffi>=0.5.0
Requires-Dist: tomli>=2.0.0; python_version < '3.11'
Requires-Dist: typer>=0.9.0
Requires-Dist: yt-dlp>=2023.3.4
Provides-Extra: api
Requires-Dist: anyio>=3.7.0; extra == 'api'
Requires-Dist: fastapi>=0.100.0; extra == 'api'
Requires-Dist: uvicorn[standard]>=0.23.0; extra == 'api'
Provides-Extra: dev
Requires-Dist: black>=24.0.0; extra == 'dev'
Requires-Dist: build>=1.0.0; extra == 'dev'
Requires-Dist: pytest-cov>=4.0.0; extra == 'dev'
Requires-Dist: pytest-mock>=3.10.0; extra == 'dev'
Requires-Dist: pytest>=7.0.0; extra == 'dev'
Requires-Dist: ruff>=0.8.0; extra == 'dev'
Requires-Dist: twine>=5.0.0; extra == 'dev'
Provides-Extra: extract
Requires-Dist: fpdf2>=2.7.0; extra == 'extract'
Requires-Dist: srt>=3.5.0; extra == 'extract'
